pyroll/hill_spreading.py
pyroll_hill_spreading-3.0.0.dist-info/METADATA
pyroll_hill_spreading-3.0.0.dist-info/WHEEL
pyroll_hill_spreading-3.0.0.dist-info/licenses/LICENSE
pyroll_hill_spreading-3.0.0.dist-info/RECORD
